LICENSE.txt
README.md
setup.py
vector_forge/__init__.py
vector_forge/constants.py
vector_forge/image_preprocessors.py
vector_forge/info_extractors.py
vector_forge/test_vectorizer.py
vector_forge/vectorizer.py
vector_forge.egg-info/PKG-INFO
vector_forge.egg-info/SOURCES.txt
vector_forge.egg-info/dependency_links.txt
vector_forge.egg-info/requires.txt
vector_forge.egg-info/top_level.txt