Metadata-Version: 2.1
Name: vector-forge
Version: 0.0.7
Summary: Easily convert individual images into feature vectors by specifying your desired model to extract meaningful representations.
Home-page: https://www.vector-forge.com/
Author: Simeon Emanuilov
Author-email: simeon.emanuilov@gmail.com
License: MIT
Keywords: vector_forge image text vector keras pytorch
Classifier: License :: OSI Approved :: MIT License
Classifier: Intended Audience :: Developers
Classifier: Intended Audience :: Education
Classifier: Intended Audience :: Science/Research
Classifier: Programming Language :: Python :: 3
Classifier: Programming Language :: Python :: 3.10
Classifier: Programming Language :: Python :: 3.11
Classifier: Programming Language :: Python :: 3 :: Only
Classifier: Topic :: Scientific/Engineering
Classifier: Topic :: Scientific/Engineering :: Mathematics
Classifier: Topic :: Scientific/Engineering :: Artificial Intelligence
Classifier: Topic :: Software Development
Classifier: Topic :: Software Development :: Libraries
Classifier: Topic :: Software Development :: Libraries :: Python Modules
Requires-Python: >=3.10
License-File: LICENSE.txt
Requires-Dist: numpy
Requires-Dist: opencv-python
Requires-Dist: transformers
Requires-Dist: torch
Requires-Dist: tensorflow
Requires-Dist: Pillow
Requires-Dist: openvino-dev
